tangent_works/__init__.py
tangent_works/__version__.py
tangent_works/api/__init__.py
tangent_works/api/anomaly_detection.py
tangent_works/api/auto_forecasting.py
tangent_works/api/forecasting.py
tangent_works/api/post_processing.py
tangent_works/api/schemas.py
tangent_works/business_data/__init__.py
tangent_works/business_data/anomaly_detection_configuration.py
tangent_works/business_data/anomaly_detection_model.py
tangent_works/business_data/forecasting_configuration.py
tangent_works/business_data/forecasting_model.py
tangent_works/business_data/imputation.py
tangent_works/business_data/sampling_period.py
tangent_works/business_data/time_scale.py
tangent_works/business_data/time_series.py
tangent_works/business_logic/__init__.py
tangent_works/business_logic/anomaly_detection_transformations.py
tangent_works/business_logic/imputation.py
tangent_works/business_logic/time_scaling.py
tangent_works/utils/__init__.py
tangent_works/utils/datetime_utils.py
tangent_works/utils/exceptions.py
tangent_works/utils/general_utils.py
tangent_works/utils/python_client_utils.py
tangent_works-1.0.2.dist-info/METADATA
tangent_works-1.0.2.dist-info/WHEEL
tangent_works-1.0.2.dist-info/RECORD
