Metadata-Version: 2.1
Name: tangent-works
Version: 1.0.2
Summary: Tangent Works Python Client.
Home-page: https://tangent.works/
Author: Tangent Works
Requires-Python: >=3.10,<4.0
Classifier: Programming Language :: Python :: 3
Classifier: Programming Language :: Python :: 3.10
Classifier: Programming Language :: Python :: 3.11
Classifier: Programming Language :: Python :: 3.12
Classifier: Programming Language :: Python :: 3.13
Requires-Dist: PyJWT (==2.8.0)
Requires-Dist: cryptography (==42.0.5)
Requires-Dist: jsonschema (==4.21.1)
Requires-Dist: numpy (==1.26.4)
Requires-Dist: pandas (==2.2.1)
Requires-Dist: requests (==2.31.0)
Requires-Dist: rsa (==4.9)
Project-URL: Documentation, https://docs.tangent.works/
